{
"id": 507,
"name": "Herdier",
"exp_type": "MEDIUM_SLOW",
"obtainable": true,
"gender_ratio": 127,
"height": 9,
"weight": 147,
"egg_groups": [
	"field"
],
"abilities": [
	{
		"id": 22,
		"name": "Intimidate"
	},
	{
		"id": 146,
		"name": "Sand Rush"
	},
	{
		"id": 113,
		"name": "Scrappy"
	}
],
"forms": [
	{
		"form_id": 0,
		"id": 507,
		"name": "Herdier"
	}
],
"evolutions": [
	{
		"id": 508,
		"name": "Stoutland",
		"type": "LEVEL",
		"val": 32
	}
],
"moves": [
	{
		"id": 33,
		"name": "Tackle",
		"type": "level",
		"level": 1
	},
	{
		"id": 43,
		"name": "Leer",
		"type": "level",
		"level": 1
	},
	{
		"id": 44,
		"name": "Bite",
		"type": "level",
		"level": 1
	},
	{
		"id": 316,
		"name": "Odor Sleuth",
		"type": "level",
		"level": 1
	},
	{
		"id": 526,
		"name": "Work Up",
		"type": "level",
		"level": 1
	},
	{
		"id": 316,
		"name": "Odor Sleuth",
		"type": "level",
		"level": 5
	},
	{
		"id": 44,
		"name": "Bite",
		"type": "level",
		"level": 8
	},
	{
		"id": 514,
		"name": "Retaliate",
		"type": "level",
		"level": 12
	},
	{
		"id": 526,
		"name": "Work Up",
		"type": "level",
		"level": 20
	},
	{
		"id": 242,
		"name": "Crunch",
		"type": "level",
		"level": 30
	},
	{
		"id": 36,
		"name": "Take Down",
		"type": "level",
		"level": 36
	},
	{
		"id": 270,
		"name": "Helping Hand",
		"type": "level",
		"level": 42
	},
	{
		"id": 179,
		"name": "Reversal",
		"type": "level",
		"level": 48
	},
	{
		"id": 46,
		"name": "Roar",
		"type": "level",
		"level": 54
	},
	{
		"id": 387,
		"name": "Last Resort",
		"type": "level",
		"level": 60
	},
	{
		"id": 416,
		"name": "Giga Impact",
		"type": "level",
		"level": 66
	},
	{
		"id": 173,
		"name": "Snore",
		"type": "move_tutor"
	},
	{
		"id": 253,
		"name": "Uproar",
		"type": "move_tutor"
	},
	{
		"id": 343,
		"name": "Covet",
		"type": "move_tutor"
	},
	{
		"id": 387,
		"name": "Last Resort",
		"type": "move_tutor"
	},
	{
		"id": 495,
		"name": "After You",
		"type": "move_tutor"
	},
	{
		"id": 36,
		"name": "Take Down",
		"type": "move_learner_tools"
	},
	{
		"id": 46,
		"name": "Roar",
		"type": "move_learner_tools"
	},
	{
		"id": 57,
		"name": "Surf",
		"type": "move_learner_tools"
	},
	{
		"id": 70,
		"name": "Strength",
		"type": "move_learner_tools"
	},
	{
		"id": 85,
		"name": "Thunderbolt",
		"type": "move_learner_tools"
	},
	{
		"id": 86,
		"name": "Thunder Wave",
		"type": "move_learner_tools"
	},
	{
		"id": 91,
		"name": "Dig",
		"type": "move_learner_tools"
	},
	{
		"id": 92,
		"name": "Toxic",
		"type": "move_learner_tools"
	},
	{
		"id": 104,
		"name": "Double Team",
		"type": "move_learner_tools"
	},
	{
		"id": 156,
		"name": "Rest",
		"type": "move_learner_tools"
	},
	{
		"id": 164,
		"name": "Substitute",
		"type": "move_learner_tools"
	},
	{
		"id": 179,
		"name": "Reversal",
		"type": "move_learner_tools"
	},
	{
		"id": 182,
		"name": "Protect",
		"type": "move_learner_tools"
	},
	{
		"id": 189,
		"name": "Mud-Slap",
		"type": "move_learner_tools"
	},
	{
		"id": 203,
		"name": "Endure",
		"type": "move_learner_tools"
	},
	{
		"id": 204,
		"name": "Charm",
		"type": "move_learner_tools"
	},
	{
		"id": 207,
		"name": "Swagger",
		"type": "move_learner_tools"
	},
	{
		"id": 213,
		"name": "Attract",
		"type": "move_learner_tools"
	},
	{
		"id": 214,
		"name": "Sleep Talk",
		"type": "move_learner_tools"
	},
	{
		"id": 216,
		"name": "Return",
		"type": "move_learner_tools"
	},
	{
		"id": 218,
		"name": "Frustration",
		"type": "move_learner_tools"
	},
	{
		"id": 237,
		"name": "Hidden Power",
		"type": "move_learner_tools"
	},
	{
		"id": 240,
		"name": "Rain Dance",
		"type": "move_learner_tools"
	},
	{
		"id": 241,
		"name": "Sunny Day",
		"type": "move_learner_tools"
	},
	{
		"id": 242,
		"name": "Crunch",
		"type": "move_learner_tools"
	},
	{
		"id": 247,
		"name": "Shadow Ball",
		"type": "move_learner_tools"
	},
	{
		"id": 249,
		"name": "Rock Smash",
		"type": "move_learner_tools"
	},
	{
		"id": 263,
		"name": "Facade",
		"type": "move_learner_tools"
	},
	{
		"id": 270,
		"name": "Helping Hand",
		"type": "move_learner_tools"
	},
	{
		"id": 290,
		"name": "Secret Power",
		"type": "move_learner_tools"
	},
	{
		"id": 304,
		"name": "Hyper Voice",
		"type": "move_learner_tools"
	},
	{
		"id": 317,
		"name": "Rock Tomb",
		"type": "move_learner_tools"
	},
	{
		"id": 332,
		"name": "Aerial Ace",
		"type": "move_learner_tools"
	},
	{
		"id": 351,
		"name": "Shock Wave",
		"type": "move_learner_tools"
	},
	{
		"id": 371,
		"name": "Payback",
		"type": "move_learner_tools"
	},
	{
		"id": 416,
		"name": "Giga Impact",
		"type": "move_learner_tools"
	},
	{
		"id": 422,
		"name": "Thunder Fang",
		"type": "move_learner_tools"
	},
	{
		"id": 423,
		"name": "Ice Fang",
		"type": "move_learner_tools"
	},
	{
		"id": 424,
		"name": "Fire Fang",
		"type": "move_learner_tools"
	},
	{
		"id": 496,
		"name": "Round",
		"type": "move_learner_tools"
	},
	{
		"id": 514,
		"name": "Retaliate",
		"type": "move_learner_tools"
	},
	{
		"id": 526,
		"name": "Work Up",
		"type": "move_learner_tools"
	},
	{
		"id": 528,
		"name": "Wild Charge",
		"type": "move_learner_tools"
	},
	{
		"id": 555,
		"name": "Snarl",
		"type": "move_learner_tools"
	}
],
"types": [
	"NORMAL",
	"NORMAL"
],
"stats": {
	"hp": 65,
	"attack": 80,
	"defense": 65,
	"speed": 60,
	"sp_attack": 35,
	"sp_defense": 65
},
"yields": {
	"exp": 130,
	"ev_hp": 0,
	"ev_attack": 2,
	"ev_defense": 0,
	"ev_speed": 0,
	"ev_sp_attack": 0,
	"ev_sp_defense": 0
},
"tiers": [
	"Untiered"
],
"held_items": [],
"locations": [
	{
		"type": "Grass",
		"region_id": 2,
		"region_name": "Unova",
		"location": "Cold Storage",
		"min_level": 19,
		"max_level": 20,
		"rarity": "Horde"
	},
	{
		"type": "Grass",
		"region_id": 2,
		"region_name": "Unova",
		"location": "Cold Storage",
		"min_level": 21,
		"max_level": 23,
		"rarity": "Very Common"
	},
	{
		"type": "Grass",
		"region_id": 2,
		"region_name": "Unova",
		"location": "Cold Storage",
		"min_level": 21,
		"max_level": 23,
		"rarity": "Very Common"
	},
	{
		"type": "Grass",
		"region_id": 2,
		"region_name": "Unova",
		"location": "Cold Storage",
		"min_level": 21,
		"max_level": 23,
		"rarity": "Very Common"
	},
	{
		"type": "Grass",
		"region_id": 2,
		"region_name": "Unova",
		"location": "Cold Storage",
		"min_level": 21,
		"max_level": 23,
		"rarity": "Very Common"
	},
	{
		"type": "Dark Grass",
		"region_id": 2,
		"region_name": "Unova",
		"location": "Cold Storage",
		"min_level": 25,
		"max_level": 27,
		"rarity": "Very Common"
	},
	{
		"type": "Dark Grass",
		"region_id": 2,
		"region_name": "Unova",
		"location": "Cold Storage",
		"min_level": 25,
		"max_level": 27,
		"rarity": "Very Common"
	},
	{
		"type": "Dark Grass",
		"region_id": 2,
		"region_name": "Unova",
		"location": "Cold Storage",
		"min_level": 25,
		"max_level": 27,
		"rarity": "Very Common"
	},
	{
		"type": "Dark Grass",
		"region_id": 2,
		"region_name": "Unova",
		"location": "Cold Storage",
		"min_level": 25,
		"max_level": 27,
		"rarity": "Very Common"
	},
	{
		"type": "Grass",
		"region_id": 2,
		"region_name": "Unova",
		"location": "P2 Laboratory",
		"min_level": 27,
		"max_level": 28,
		"rarity": "Horde"
	},
	{
		"type": "Grass",
		"region_id": 2,
		"region_name": "Unova",
		"location": "P2 Laboratory",
		"min_level": 28,
		"max_level": 31,
		"rarity": "Very Common"
	},
	{
		"type": "Dark Grass",
		"region_id": 2,
		"region_name": "Unova",
		"location": "Route 1",
		"min_level": 32,
		"max_level": 34,
		"rarity": "Very Common"
	},
	{
		"type": "Grass",
		"region_id": 2,
		"region_name": "Unova",
		"location": "Route 10",
		"min_level": 32,
		"max_level": 33,
		"rarity": "Horde"
	},
	{
		"type": "Grass",
		"region_id": 2,
		"region_name": "Unova",
		"location": "Route 10",
		"min_level": 33,
		"max_level": 34,
		"rarity": "Common"
	},
	{
		"type": "Dark Grass",
		"region_id": 2,
		"region_name": "Unova",
		"location": "Route 10",
		"min_level": 38,
		"max_level": 39,
		"rarity": "Common"
	},
	{
		"type": "Dark Grass",
		"region_id": 2,
		"region_name": "Unova",
		"location": "Route 10",
		"min_level": 39,
		"max_level": 39,
		"rarity": "Horde"
	}
]
}